<armourHeadBlueprint name="EMPTY"> <!--Template blueprint, any tag which is not present in a blueprint will default to the value in this one. The blueprint name is used by the game to identify it-->
	<name></name> <!--The name as it appears in game-->
	<description></description> <!--The description in game-->
	<!-- Modifiers -->
	<maxHealthModifier>0</maxHealthModifier> <!--Max health-->
	<maxManaModifier>0</maxManaModifier> <!--Max mana-->
	<turnManaRegenModifier>0</turnManaRegenModifier> <!--Mana regenerated per turn-->
	<battleManaRegenModifier>0</battleManaRegenModifier> <!--Mana regenerated at end of battle -->
	<constRegenModifier>0</constRegenModifier> <!--Health regenerated per turn-->
	<battleRegenModifier>0</battleRegenModifier> <!--Health regen after battle-->
	<flatArmourModifier>0</flatArmourModifier> <!--Physical armour-->
	<propArmourModifier>0</propArmourModifier> <!--Proportional physical damage reduction, this is the increase-->
	<flatMagicArmourModifier>0</flatMagicArmourModifier> <!--Magic armour-->
	<propMagicArmourModifier>0</propMagicArmourModifier> <!--Proportional magic armour-->
	<flatDamageModifier>0</flatDamageModifier> <!--Modifier for outgoing physical damage-->
	<propDamageModifier>0</propDamageModifier> <!--Proportional physical damage modifier-->
	<flatMagicDamageModifier>0</flatMagicDamageModifier> <!--Outgoing magic damage-->
	<propMagicDamageModifier>0</propMagicDamageModifier> <!--proportional magic damage-->
	<flatArmourPiercingDamageModifier>0</flatArmourPiercingDamageModifier> <!--AP damage-->
	<propArmourPiercingDamageModifier>0</propArmourPiercingDamageModifier> <!--Proportional AP damage-->
	<evadeChanceModifier>0</evadeChanceModifier> <!--Evade chance, this is proportional-->
	<poisonResistModifier>0</poisonResistModifier> <!--Poison resist-->
	<bleedResistModifier>0</bleedResistModifier> <!--Bleed resist-->
	<counterAttackChanceModifier>0</counterAttackChanceModifier> <!--Counter attack chance-->
	<bonusActionsModifier>0</bonusActionsModifier><!--Number of bonus actions each turn-->
	<initiativeModifier>0</initiativeModifier><!--Modifies speed-->
	<upgrade>EMPTY</upgrade><!--The name of the blueprint containing the upgraded version. If this is EMPTY or omitted, it cannot be upgraded-->
</armourHeadBlueprint>

<armourHeadBlueprint name="IRON_HELMET_1">
	<name>Iron Helmet</name>
	<description>A strong iron helmet providing good physical protection, its weight can slow down the wearer.</description>
	<maxHealthModifier>5</maxHealthModifier>
	<flatArmourModifier>2</flatArmourModifier>
	<evadeChanceModifier>-0.1</evadeChanceModifier>
	<counterAttackChanceModifier>-0.1</counterAttackChanceModifier>
	<initiativeModifier>-1</initiativeModifier>
</armourHeadBlueprint>

<armourTorsoBlueprint name="IRON_CHESTPLATE_1">
	<name>Iron Chestplate</name>
	<description>A strong iron chestplate providing good physical protection, its weight can slow down the wearer.</description>
	<maxHealthModifier>10</maxHealthModifier>
	<flatArmourModifier>4</flatArmourModifier>
	<evadeChanceModifier>-0.2</evadeChanceModifier>
	<counterAttackChanceModifier>-0.2</counterAttackChanceModifier>
	<initiativeModifier>-2</initiativeModifier>
</armourTorsoBlueprint>

<armourLegsBlueprint name="IRON_GREAVES_1">
	<name>Iron Greaves</name>
	<description>Strong iron greaves providing good physical protection, their weight can slow down the wearer.</description>
	<maxHealthModifier>5</maxHealthModifier>
	<flatArmourModifier>2</flatArmourModifier>
	<evadeChanceModifier>-0.1</evadeChanceModifier>
	<counterAttackChanceModifier>-0.1</counterAttackChanceModifier>
	<initiativeModifier>-1</initiativeModifier>
</armourLegsBlueprint>

<armourFeetBlueprint name="IRON_BOOTS_1">
	<name>Iron Boots</name>
	<description>Strong iron boots providing good physical protection, their weight can slow down the wearer.</description>
	<maxHealthModifier>5</maxHealthModifier>
	<flatArmourModifier>2</flatArmourModifier>
	<evadeChanceModifier>-0.1</evadeChanceModifier>
	<counterAttackChanceModifier>-0.1</counterAttackChanceModifier>
	<initiativeModifier>-1</initiativeModifier>
</armourFeetBlueprint>

<armourHeadBlueprint name="LEATHER_HELMET_1">
	<name>Leather Cap</name>
	<description>A leather cap, providing moderate physical protection without restricting movement.</description>
	<flatArmourModifier>1</flatArmourModifier>
	<evadeChanceModifier>0.1</evadeChanceModifier>
	<counterAttackChanceModifier>0.1</counterAttackChanceModifier>
</armourHeadBlueprint>

<armourTorsoBlueprint name="LEATHER_CHESTPLATE_1">
	<name>Leather Cuirass</name>
	<description>A leather cuirass, providing moderate physical protection without restricting movement.</description>
	<flatArmourModifier>2</flatArmourModifier>
	<evadeChanceModifier>0.2</evadeChanceModifier>
	<counterAttackChanceModifier>0.2</counterAttackChanceModifier>
</armourTorsoBlueprint>

<armourLegsBlueprint name="LEATHER_GREAVES_1">
	<name>Leather Leggings</name>
	<description>Leather leggings, providing moderate physical protection without restricting movement.</description>
	<flatArmourModifier>1</flatArmourModifier>
	<evadeChanceModifier>0.1</evadeChanceModifier>
	<counterAttackChanceModifier>0.1</counterAttackChanceModifier>
</armourLegsBlueprint>

<armourFeetBlueprint name="LEATHER_BOOTS_1">
	<name>Leather Boots</name>
	<description>Leather boots, providing moderate physical protection without restricting movement.</description>
	<flatArmourModifier>1</flatArmourModifier>
	<evadeChanceModifier>0.1</evadeChanceModifier>
	<counterAttackChanceModifier>0.1</counterAttackChanceModifier>
</armourFeetBlueprint>

<armourTorsoBlueprint name="ROBES_1">
	<name>Robes</name>
	<description>Basic wizard robes, they offer little physical protection, but improve mana regeneration capabilities.</description>
	<maxManaModifier>10</maxManaModifier>
	<turnManaRegenModifier>5</turnManaRegenModifier>
	<battleManaRegenModifier>10</battleManaRegenModifier>
	<flatArmourModifier>2</flatArmourModifier>
</armourTorsoBlueprint>